pythondata_cpu_marocchino/__init__.py
pythondata_cpu_marocchino/verilog/.travis.yml
pythondata_cpu_marocchino/verilog/Jenkinsfile
pythondata_cpu_marocchino/verilog/LICENSE
pythondata_cpu_marocchino/verilog/README.md
pythondata_cpu_marocchino/verilog/or1k_marocchino.core
pythondata_cpu_marocchino/verilog/.travis/run-or1k-tests.sh
pythondata_cpu_marocchino/verilog/.travis/run-verilator.sh
pythondata_cpu_marocchino/verilog/.travis/test.sh
pythondata_cpu_marocchino/verilog/bench/verilog/or1k_marocchino_monitor.v
pythondata_cpu_marocchino/verilog/bench/verilog/or1k_marocchino_traceport_monitor.v
pythondata_cpu_marocchino/verilog/doc/readme/fp_comparisons_table.odt
pythondata_cpu_marocchino/verilog/doc/readme/marrochino_1_goal.txt
pythondata_cpu_marocchino/verilog/doc/readme/marrochino_2_status.txt
pythondata_cpu_marocchino/verilog/doc/readme/marrochino_3_how_to.txt
pythondata_cpu_marocchino/verilog/rtl/verilog/or1k_cfgrs.v
pythondata_cpu_marocchino/verilog/rtl/verilog/or1k_defines.v
pythondata_cpu_marocchino/verilog/rtl/verilog/or1k_dpram_en_w1st.v
pythondata_cpu_marocchino/verilog/rtl/verilog/or1k_marocchino_bus_if_wb32.v
pythondata_cpu_marocchino/verilog/rtl/verilog/or1k_marocchino_cache_lru.v
pythondata_cpu_marocchino/verilog/rtl/verilog/or1k_marocchino_cpu.v
pythondata_cpu_marocchino/verilog/rtl/verilog/or1k_marocchino_ctrl.v
pythondata_cpu_marocchino/verilog/rtl/verilog/or1k_marocchino_dcache.v
pythondata_cpu_marocchino/verilog/rtl/verilog/or1k_marocchino_decode.v
pythondata_cpu_marocchino/verilog/rtl/verilog/or1k_marocchino_dmmu.v
pythondata_cpu_marocchino/verilog/rtl/verilog/or1k_marocchino_fetch.v
pythondata_cpu_marocchino/verilog/rtl/verilog/or1k_marocchino_icache.v
pythondata_cpu_marocchino/verilog/rtl/verilog/or1k_marocchino_immu.v
pythondata_cpu_marocchino/verilog/rtl/verilog/or1k_marocchino_int_1clk.v
pythondata_cpu_marocchino/verilog/rtl/verilog/or1k_marocchino_int_div.v
pythondata_cpu_marocchino/verilog/rtl/verilog/or1k_marocchino_int_mul.v
pythondata_cpu_marocchino-0.0.post209.dist-info/LICENSE
pythondata_cpu_marocchino-0.0.post209.dist-info/METADATA
pythondata_cpu_marocchino-0.0.post209.dist-info/WHEEL
pythondata_cpu_marocchino-0.0.post209.dist-info/top_level.txt
pythondata_cpu_marocchino-0.0.post209.dist-info/RECORD
