Metadata-Version: 2.1
Name: pythondata-cpu-marocchino
Version: 0.0.post209
Summary: Python module containing verilog files for Marocchino cpu.
Home-page: https://github.com/litex-hub/pythondata-cpu-marocchino
Author: LiteX Authors
Author-email: litex@googlegroups.com
Project-URL: Bug Tracker, https://github.com/litex-hub/pythondata-cpu-marocchino/issues
Project-URL: Source Code, https://github.com/litex-hub/pythondata-cpu-marocchino
Classifier: Programming Language :: Python :: 3
Classifier: License :: OSI Approved :: Mozilla Public License 2.0 (MPL 2.0)
Classifier: Operating System :: OS Independent
Requires-Python: >=3.5
License-File: LICENSE
